fastplate/__init__.py
fastplate/main.py
fastplate/template/.gitignore
fastplate/template/Dockerfile
fastplate/template/GEMINI.md
fastplate/template/LICENSE
fastplate/template/Makefile
fastplate/template/README.md
fastplate/template/docker-compose.yml
fastplate/template/pyproject.toml
fastplate/template/app/__init__.py
fastplate/template/app/main.py
fastplate/template/app/api/__init__.py
fastplate/template/app/core/__init__.py
fastplate/template/app/core/config.py
fastplate/template/app/core/middleware.py
fastplate/template/app/models/__init__.py
fastplate/template/app/schemas/__init__.py
fastplate/template/app/services/__init__.py
fastplate/template/app/views/__init__.py
fastplate/template/app/views/index.py
fastplate/template/frontend/package-lock.json
fastplate/template/frontend/package.json
fastplate/template/frontend/static/css/input.css
fastplate/template/frontend/static/css/output.css
fastplate/template/frontend/templates/base.html
fastplate/template/frontend/templates/components/card.html
fastplate/template/frontend/templates/components/navbar.html
fastplate/template/frontend/templates/pages/index.html
fastplate/template/frontend/templates/pages/styletest.html
fastplate-0.1.0.dist-info/METADATA
fastplate-0.1.0.dist-info/WHEEL
fastplate-0.1.0.dist-info/entry_points.txt
fastplate-0.1.0.dist-info/licenses/LICENSE
fastplate-0.1.0.dist-info/RECORD
