Metadata-Version: 2.4
Name: fastplate
Version: 0.1.0
Summary: CLI to scaffold FastAPI projects with Tailwind CSS, DaisyUI, and Jinja2 templates
Project-URL: Repository, https://github.com/MichielMe/fastplate
Author-email: Michiel Meire <michiel.meire@hotmail.com>
License-Expression: MIT
License-File: LICENSE
Keywords: cli,daisyui,fastapi,framework,jinja2,scaffold,tailwind,tailwindcss,template,web
Classifier: Development Status :: 4 - Beta
Classifier: Environment :: Console
Classifier: Framework :: FastAPI
Classifier: Intended Audience :: Developers
Classifier: License :: OSI Approved :: MIT License
Classifier: Operating System :: OS Independent
Classifier: Programming Language :: Python :: 3
Classifier: Programming Language :: Python :: 3.12
Classifier: Programming Language :: Python :: 3.13
Classifier: Programming Language :: Python :: 3.14
Classifier: Topic :: Internet :: WWW/HTTP
Classifier: Topic :: Software Development :: Code Generators
Classifier: Typing :: Typed
Requires-Python: >=3.12
Requires-Dist: click>=8.0.0
